strategy/__init__.py
strategy/account.py
strategy/account_data.py
strategy/backtest.py
strategy/candle.py
strategy/chainable.py
strategy/common.py
strategy/config.py
strategy/currency.py
strategy/exchange.py
strategy/expression.py
strategy/framework.py
strategy/futures.py
strategy/index.py
strategy/indicator.py
strategy/market_data.py
strategy/okex.py
strategy/okex_for_spot.py
strategy/okex_trade.py
strategy/orderbook.py
strategy/singleton.py
strategy/store.py
strategy/technical_analysis.py
strategy/ticker.py
strategy/trade.py
strategy/trade_tool.py
strategy/tradetest.py
strategy/utf8logger.py
strategy/volume.py
stream/__init__.py
stream/offline.py
stream/online.py
stream/streaming.py
mathlab_strategy_v2_andrete-0.0.2.dist-info/LICENSE
mathlab_strategy_v2_andrete-0.0.2.dist-info/METADATA
mathlab_strategy_v2_andrete-0.0.2.dist-info/WHEEL
mathlab_strategy_v2_andrete-0.0.2.dist-info/top_level.txt
mathlab_strategy_v2_andrete-0.0.2.dist-info/RECORD
